[{"name":"Ромашки",
"color":"4",
"explicit":"no",
"additional":"single",
"artist":"Karna.val",
"artist_uri":"[{\"info_en\":\"Artist\",\"info_ru\":\"Артист\",\"info_de\":\"Interpret:in\",\"name\":\"Karna.val\",\"image\":\"/Karna.val/image.jpg\",\"link\":\"/Karna.val/link.json\"}]",
"genre_en":"Pop","genre_de":"Pop","genre_ru":"Поп",
"release":"2021",
"date":"10","month":"Jun","year":"2021",
"songs_num":"1","songs_add":"1",
"min":"2","min_add":"2","sec":"28","sec_add":"3",
"copyright":"℗ 2021 KOALA MUSIC",
"image":"/Karna.val/Romashki/imagehd.jpg",
"image4k":"/Karna.val/Romashki/image4k.jpg",
"songs":"[{\"number\":\"1\",\"time\":\"02:01\",\"name\":\"Ромашки\",\"artist\":\"Karna.val\",\"star\":\"yes\",\"explicit\":\"no\",\"link\":\"/Karna.val/Romashki/Romashki/link.json\"}]"}]